README.md
setup.cfg
setup.py
eis/__init__.py
eis/product_sync/__init__.py
eis/product_sync/api_client.py
eis/product_sync/configuration.py
eis/product_sync/exceptions.py
eis/product_sync/model_utils.py
eis/product_sync/rest.py
eis/product_sync/api/__init__.py
eis/product_sync/api/default_api.py
eis/product_sync/api/products_api.py
eis/product_sync/api/tasks_api.py
eis/product_sync/apis/__init__.py
eis/product_sync/model/__init__.py
eis/product_sync/model/create_product_request_dto.py
eis/product_sync/model/create_product_response_class.py
eis/product_sync/model/create_product_version_request_dto.py
eis/product_sync/model/create_product_version_response_class.py
eis/product_sync/model/get_environment_info_response_class.py
eis/product_sync/model/get_task_product_details_response_class.py
eis/product_sync/model/get_task_status_response_class.py
eis/product_sync/model/inline_response200.py
eis/product_sync/model/inline_response503.py
eis/product_sync/model/list_products_response_class.py
eis/product_sync/model/list_task_logs_response_class.py
eis/product_sync/model/list_tasks_response_class.py
eis/product_sync/model/product_class.py
eis/product_sync/model/product_version_class.py
eis/product_sync/model/start_compare_task_request_dto.py
eis/product_sync/model/start_compare_task_response_class.py
eis/product_sync/model/start_copy_task_request_dto.py
eis/product_sync/model/start_copy_task_response_class.py
eis/product_sync/model/start_export_task_request_dto.py
eis/product_sync/model/start_export_task_response_class.py
eis/product_sync/model/start_sync_task_request_dto.py
eis/product_sync/model/start_sync_task_response_class.py
eis/product_sync/model/stop_task_request_dto.py
eis/product_sync/model/stop_task_response_class.py
eis/product_sync/model/task_class.py
eis/product_sync/model/task_log_class.py
eis/product_sync/models/__init__.py
eis_product_sync.egg-info/PKG-INFO
eis_product_sync.egg-info/SOURCES.txt
eis_product_sync.egg-info/dependency_links.txt
eis_product_sync.egg-info/requires.txt
eis_product_sync.egg-info/top_level.txt
test/test_create_product_request_dto.py
test/test_create_product_response_class.py
test/test_create_product_version_request_dto.py
