Metadata-Version: 2.1
Name: eis-product-sync
Version: 1.4.0
Summary: EMIL ProductSyncService
Home-page: UNKNOWN
Author: Contact us
Author-email: kontakt@emil.de
License: UNKNOWN
Keywords: OpenAPI,OpenAPI-Generator,EMIL ProductSyncService
Platform: UNKNOWN
Requires-Python: >=3.6
